boa3/__init__.py
boa3/boa3.py
boa3/cli.py
boa3/cpm.py
boa3/internal/__init__.py
boa3/internal/constants.py
boa3/internal/deprecation.py
boa3/internal/env.py
boa3/internal/utils.py
boa3/internal/analyser/__init__.py
boa3/internal/analyser/analyser.py
boa3/internal/analyser/astanalyser.py
boa3/internal/analyser/asthelper.py
boa3/internal/analyser/astoptimizer.py
boa3/internal/analyser/builtinfunctioncallanalyser.py
boa3/internal/analyser/constructanalyser.py
boa3/internal/analyser/importanalyser.py
boa3/internal/analyser/moduleanalyser.py
boa3/internal/analyser/typeanalyser.py
boa3/internal/analyser/model/ManifestSymbol.py
boa3/internal/analyser/model/__init__.py
boa3/internal/analyser/model/functionarguments.py
boa3/internal/analyser/model/symbolscope.py
boa3/internal/analyser/model/optimizer/Operation.py
boa3/internal/analyser/model/optimizer/__init__.py
boa3/internal/analyser/supportedstandard/__init__.py
boa3/internal/analyser/supportedstandard/standardanalyser.py
boa3/internal/cli_commands/__init__.py
boa3/internal/cli_commands/compile_command.py
boa3/internal/cli_commands/icommand.py
boa3/internal/compiler/__init__.py
boa3/internal/compiler/compiledmetadata.py
boa3/internal/compiler/compiler.py
boa3/internal/compiler/compileroutput.py
boa3/internal/compiler/codegenerator/__init__.py
boa3/internal/compiler/codegenerator/codegenerator.py
boa3/internal/compiler/codegenerator/codegeneratorvisitor.py
boa3/internal/compiler/codegenerator/codeoptimizer.py
boa3/internal/compiler/codegenerator/generatordata.py
boa3/internal/compiler/codegenerator/initstatementsvisitor.py
boa3/internal/compiler/codegenerator/methodtokencollection.py
boa3/internal/compiler/codegenerator/optimizerhelper.py
boa3/internal/compiler/codegenerator/variablegenerationdata.py
boa3/internal/compiler/codegenerator/vmcodemap.py
boa3/internal/compiler/codegenerator/vmcodemapping.py
boa3/internal/compiler/codegenerator/engine/__init__.py
boa3/internal/compiler/codegenerator/engine/executionscript.py
neo3_boa-1.4.1.dist-info/licenses/LICENSE
neo3_boa-1.4.1.dist-info/METADATA
neo3_boa-1.4.1.dist-info/WHEEL
neo3_boa-1.4.1.dist-info/entry_points.txt
neo3_boa-1.4.1.dist-info/top_level.txt
neo3_boa-1.4.1.dist-info/RECORD
