Metadata-Version: 2.4
Name: neo3-boa
Version: 1.4.1
Summary: A Python compiler for the Neo3 Virtual Machine
License-Expression: MIT
Project-URL: repository, https://github.com/CityOfZion/neo3-boa
Project-URL: documentation, https://dojo.coz.io/neo3/boa/index.html
Project-URL: changelog, https://github.com/CityOfZion/neo3-boa/blob/master/CHANGELOG.md
Keywords: compiler,NEO,.nef,blockchain,smartcontract,development,dApp
Classifier: Development Status :: 5 - Production/Stable
Classifier: Intended Audience :: Developers
Classifier: Topic :: Software Development :: Build Tools
Classifier: Programming Language :: Python :: 3.12
Classifier: Programming Language :: Python :: 3.13
Requires-Python: <3.14,>=3.12
License-File: LICENSE
Requires-Dist: base58>=1.0.3
Requires-Dist: deprecation>=2.1.0
Requires-Dist: wheel>=0.30.0
Requires-Dist: requests==2.31.0
Provides-Extra: dev
Requires-Dist: autopep8>=1.4.4; extra == "dev"
Requires-Dist: bump-my-version==0.10.0; extra == "dev"
Requires-Dist: coverage>=6.0.1; extra == "dev"
Requires-Dist: filelock>=3.10.7; extra == "dev"
Requires-Dist: pycodestyle>=2.11.1; extra == "dev"
Requires-Dist: twine>=1.10.0; extra == "dev"
Provides-Extra: test
Requires-Dist: boa-test-constructor>=0.4.0; extra == "test"
Provides-Extra: docs
Requires-Dist: autodocsumm>=0.2.12; extra == "docs"
Requires-Dist: myst-parser==4.0.1; extra == "docs"
Requires-Dist: Sphinx==8.2.3; extra == "docs"
Requires-Dist: sphinx-rtd-theme==3.0.2; extra == "docs"
Dynamic: license-file
